setup.py
czy_ld/__init__.py
czy_ld/czy_ld.py
czy_ld.egg-info/PKG-INFO
czy_ld.egg-info/SOURCES.txt
czy_ld.egg-info/dependency_links.txt
czy_ld.egg-info/top_level.txt