Metadata-Version: 1.0
Name: czy-ld
Version: 1.2
Summary: Recursively delete the remaining folders
Home-page: https://www.cnblogs.com/RainBol/
Author: Rainbol
Author-email: 2497643794@qq.com
License: UNKNOWN
Platform: UNKNOWN
